nrel_rex-0.4.3.dist-info/licenses/LICENSE
rex/__init__.py
rex/bias_correction.py
rex/multi_file_resource.py
rex/multi_res_resource.py
rex/multi_time_resource.py
rex/multi_year_resource.py
rex/outputs.py
rex/renewable_resource.py
rex/resource.py
rex/sam_resource.py
rex/version.py
rex/external/__init__.py
rex/external/encodings.json
rex/external/rexarray.py
rex/external/standard_attrs.json
rex/joint_pd/__init__.py
rex/joint_pd/joint_pd.py
rex/joint_pd/wind_rose_cli.py
rex/rechunk_h5/__init__.py
rex/rechunk_h5/chunk_size.py
rex/rechunk_h5/combine_h5.py
rex/rechunk_h5/combine_h5_cli.py
rex/rechunk_h5/rechunk_cli.py
rex/rechunk_h5/rechunk_h5.py
rex/resource_extraction/README.rst
rex/resource_extraction/US_wave_cli.py
rex/resource_extraction/__init__.py
rex/resource_extraction/multi_year_resource_cli.py
rex/resource_extraction/nsrdb_cli.py
rex/resource_extraction/resource_cli.py
rex/resource_extraction/resource_extraction.py
rex/resource_extraction/wave_cli.py
rex/resource_extraction/wind_cli.py
rex/temporal_stats/__init__.py
rex/temporal_stats/temporal_stats.py
rex/temporal_stats/temporal_stats_cli.py
rex/utilities/__init__.py
rex/utilities/bc_parse_table.py
rex/utilities/bc_utils.py
rex/utilities/cli_dtypes.py
rex/utilities/downscale.py
rex/utilities/exceptions.py
rex/utilities/execution.py
rex/utilities/fun_utils.py
rex/utilities/hpc.py
rex/utilities/loggers.py
rex/utilities/parse_keys.py
rex/utilities/regridder.py
rex/utilities/solar_position.py
rex/utilities/toml_parser.py
rex/utilities/utilities.py
nrel_rex-0.4.3.dist-info/METADATA
nrel_rex-0.4.3.dist-info/WHEEL
nrel_rex-0.4.3.dist-info/entry_points.txt
nrel_rex-0.4.3.dist-info/top_level.txt
nrel_rex-0.4.3.dist-info/RECORD
