Metadata-Version: 2.4
Name: NREL-rex
Version: 0.4.3
Summary: National Renewable Energy Laboratory's (NREL's) REsource eXtraction tool: rex
Author-email: Michael Rossol <michael.rossol@nrel.gov>
Maintainer-email: Grant Buster <gbuster@nrel.gov>, Paul Pinchuk <ppinchuk@nrel.gov>, Brandon Benton <brandon.benton@nrel.gov>
License-Expression: BSD-3-Clause
Project-URL: homepage, https://www2.nrel.gov/gis/renewable-energy-potential
Project-URL: documentation, https://nrel.github.io/rex/
Project-URL: repository, https://github.com/NREL/rex
Keywords: rex,NREL
Classifier: Development Status :: 4 - Beta
Classifier: Intended Audience :: Science/Research
Classifier: Natural Language :: English
Classifier: Programming Language :: Python :: 3.9
Classifier: Programming Language :: Python :: 3.10
Classifier: Programming Language :: Python :: 3.11
Classifier: Programming Language :: Python :: 3.12
Classifier: Programming Language :: Python :: 3.13
Requires-Python: >=3.9
License-File: LICENSE
Requires-Dist: click>=8.1.8
Requires-Dist: fsspec>=2021.09.0
Requires-Dist: dask>=2024.8.0
Requires-Dist: h5py>=3.13.0
Requires-Dist: h5pyd>=0.18.0
Requires-Dist: numpy>=2.0.2
Requires-Dist: pandas>=2.2.3
Requires-Dist: packaging>=24.2
Requires-Dist: psutil>=7.0.0
Requires-Dist: PyYAML>=6.0.2
Requires-Dist: s3fs>=2023.6.0
Requires-Dist: scikit-learn>=1.6.1
Requires-Dist: scipy>=1.3
Requires-Dist: toml>=0.10.2
Requires-Dist: xarray>=2024.07.0
Provides-Extra: test
Requires-Dist: pytest<9,>=8.3.5; extra == "test"
Requires-Dist: pytest-timeout<3,>=2.3.1; extra == "test"
Requires-Dist: flaky<4,>=3.8.1; extra == "test"
Requires-Dist: NREL-PySAM>=7.0.0; extra == "test"
Provides-Extra: dev
Requires-Dist: flake8; extra == "dev"
Requires-Dist: pre-commit; extra == "dev"
Requires-Dist: pylint; extra == "dev"
Provides-Extra: hsds
Requires-Dist: hsds>=0.8.4; extra == "hsds"
Provides-Extra: build
Requires-Dist: build<2,>=1.2.2; extra == "build"
Requires-Dist: pkginfo<2,>=1.12.1.2; extra == "build"
Requires-Dist: twine<7,>=6.1.0; extra == "build"
Dynamic: license-file
